polyblur/__init__.py
polyblur/blur_estimation.py
polyblur/deblurring.py
polyblur/domain_transform.py
polyblur/edgetaper.py
polyblur/filters.py
polyblur/utils.py
polyblur-0.1.3.dist-info/LICENSE
polyblur-0.1.3.dist-info/METADATA
polyblur-0.1.3.dist-info/WHEEL
polyblur-0.1.3.dist-info/top_level.txt
polyblur-0.1.3.dist-info/RECORD
