Metadata-Version: 2.1
Name: polyblur
Version: 0.1.3
Summary: Breaking down Polyblur: Fast blind Correction of Small Anisotropic Blurs [IPOL2022]
Home-page: https://github.com/teboli/polyblur
Author: Thomas Eboli
Author-email: thomas.eboli@ens-paris-saclay.fr
Classifier: Programming Language :: Python :: 3
Classifier: License :: OSI Approved :: MIT License
Classifier: Environment :: GPU :: NVIDIA CUDA
Classifier: Operating System :: MacOS :: MacOS X
Classifier: Operating System :: POSIX
Classifier: Topic :: Scientific/Engineering :: Image Processing
License-File: LICENSE
